ApacheFreemarker2328ZhongwenWendang/README.md
ApacheFreemarker2328ZhongwenWendang/__init__.py
ApacheFreemarker2328ZhongwenWendang/__main__.py
ApacheFreemarker2328ZhongwenWendang/file.epub
ApacheFreemarker2328ZhongwenWendang/index.html
ApacheFreemarker2328ZhongwenWendang/css/__init__.py
ApacheFreemarker2328ZhongwenWendang/css/annotations.css
ApacheFreemarker2328ZhongwenWendang/css/main.css
ApacheFreemarker2328ZhongwenWendang/css/normalize.css
ApacheFreemarker2328ZhongwenWendang/css/popup.css
ApacheFreemarker2328ZhongwenWendang/font/__init__.py
ApacheFreemarker2328ZhongwenWendang/font/fontello.eot
ApacheFreemarker2328ZhongwenWendang/font/fontello.svg
ApacheFreemarker2328ZhongwenWendang/font/fontello.ttf
ApacheFreemarker2328ZhongwenWendang/font/fontello.woff
ApacheFreemarker2328ZhongwenWendang/img/__init__.py
ApacheFreemarker2328ZhongwenWendang/img/annotator-glyph-sprite.png
ApacheFreemarker2328ZhongwenWendang/img/annotator-icon-sprite.png
ApacheFreemarker2328ZhongwenWendang/img/apple-touch-icon.png
ApacheFreemarker2328ZhongwenWendang/img/cancelfullscreen.png
ApacheFreemarker2328ZhongwenWendang/img/close.png
ApacheFreemarker2328ZhongwenWendang/img/fullscreen.png
ApacheFreemarker2328ZhongwenWendang/img/loader.gif
ApacheFreemarker2328ZhongwenWendang/img/menu-icon.png
ApacheFreemarker2328ZhongwenWendang/img/save.png
ApacheFreemarker2328ZhongwenWendang/img/saved.png
ApacheFreemarker2328ZhongwenWendang/img/settings-s.png
ApacheFreemarker2328ZhongwenWendang/img/settings.png
ApacheFreemarker2328ZhongwenWendang/img/star.png
ApacheFreemarker2328ZhongwenWendang/js/__init__.py
ApacheFreemarker2328ZhongwenWendang/js/epub.js
ApacheFreemarker2328ZhongwenWendang/js/epub.min.js
ApacheFreemarker2328ZhongwenWendang/js/epub.min.map
ApacheFreemarker2328ZhongwenWendang/js/hooks.min.js
ApacheFreemarker2328ZhongwenWendang/js/hooks.min.map
ApacheFreemarker2328ZhongwenWendang/js/reader.js
ApacheFreemarker2328ZhongwenWendang/js/reader.js.map
ApacheFreemarker2328ZhongwenWendang/js/reader.min.js
apache_freemarker_2_3_28_zhongwen_wendang-2024.3.4.0.dist-info/METADATA
apache_freemarker_2_3_28_zhongwen_wendang-2024.3.4.0.dist-info/WHEEL
apache_freemarker_2_3_28_zhongwen_wendang-2024.3.4.0.dist-info/entry_points.txt
apache_freemarker_2_3_28_zhongwen_wendang-2024.3.4.0.dist-info/top_level.txt
apache_freemarker_2_3_28_zhongwen_wendang-2024.3.4.0.dist-info/RECORD
